.bumpversion.cfg
.cookiecutterrc
.coveragerc
.editorconfig
.travis.yml
AUTHORS.rst
CHANGELOG.rst
CONTRIBUTING.rst
LICENSE
MANIFEST.in
README.rst
setup.cfg
setup.py
tox.ini
ci/bootstrap.py
ci/templates/.travis.yml
docs/authors.rst
docs/changelog.rst
docs/conf.py
docs/contributing.rst
docs/index.rst
docs/installation.rst
docs/readme.rst
docs/requirements.txt
docs/spelling_wordlist.txt
docs/usage.rst
docs/reference/index.rst
docs/reference/mapy.rst
src/hexmap/__init__.py
src/hexmap/map.c
src/hexmap.egg-info/PKG-INFO
src/hexmap.egg-info/SOURCES.txt
src/hexmap.egg-info/dependency_links.txt
src/hexmap.egg-info/not-zip-safe
src/hexmap.egg-info/top_level.txt
tests/test_mapy.py